analysis/__init__.py
analysis/gitauthor.py
analysis/gitauthors.py
analysis/gitdata.py
analysis/gitrepository.py
analysis/gitrevision.py
analysis/gittags.py
analysis/repostat.py
report/__init__.py
report/colormaps.py
report/html_page.py
report/htmlreportcreator.py
report/assets/d3.v3.min.js
report/assets/gitstats.css
report/assets/nv.d3.css
report/assets/nv.d3.min.js
report/assets/sortable.js
report/assets/images/arrow-down.gif
report/assets/images/arrow-none.gif
report/assets/images/arrow-up.gif
report/templates/about.html
report/templates/activity.html
report/templates/activity.js
report/templates/authors.html
report/templates/authors.js
report/templates/base.html
report/templates/files.html
report/templates/files.js
report/templates/general.html
report/templates/tags.html
tools/__init__.py
tools/check_report_files.py
tools/configuration.py
tools/packages_info.py
tools/release_data.json
tools/timeit.py
repostat_app-2.2.0.dist-info/LICENSE
repostat_app-2.2.0.dist-info/METADATA
repostat_app-2.2.0.dist-info/WHEEL
repostat_app-2.2.0.dist-info/entry_points.txt
repostat_app-2.2.0.dist-info/top_level.txt
repostat_app-2.2.0.dist-info/RECORD
