Metadata-Version: 2.1
Name: repostat-app
Version: 2.2.0
Summary: Desktop git repository analyser and report creator.
Home-page: https://github.com/vifactor/repostat
Author: Viktor Kopp
Author-email: vifactor@gmail.com
License: GPLv3
Keywords: git analysis statistics vcs python visualization
Platform: UNKNOWN
Classifier: Development Status :: 5 - Production/Stable
Classifier: Environment :: Console
Classifier: Intended Audience :: Developers
Classifier: Intended Audience :: Science/Research
Classifier: Intended Audience :: Education
Classifier: Programming Language :: Python :: 3.6
Classifier: Programming Language :: Python :: 3.7
Classifier: License :: OSI Approved :: GNU General Public License v2 or later (GPLv2+)
Classifier: Topic :: Software Development :: Version Control
Classifier: Topic :: Utilities
Classifier: Operating System :: OS Independent
Classifier: Operating System :: POSIX
Classifier: Operating System :: MacOS :: MacOS X
Classifier: Operating System :: Microsoft :: Windows
Requires-Python: >3.5
Requires-Dist: Jinja2 (>=2.10.1)
Requires-Dist: pygit2 (>=1.0.3)
Requires-Dist: pytz (>=2018.5)
Requires-Dist: pandas (~=0.25.3)
Requires-Dist: tqdm (~=4.45.0)
